MANIFEST.in
README.rst
setup.py
test/test_async_timeout.py
test/test_barcode.py
zcbot_crawl_core/__init__.py
zcbot_crawl_core.egg-info/PKG-INFO
zcbot_crawl_core.egg-info/SOURCES.txt
zcbot_crawl_core.egg-info/dependency_links.txt
zcbot_crawl_core.egg-info/requires.txt
zcbot_crawl_core.egg-info/top_level.txt
zcbot_crawl_core/client/__init__.py
zcbot_crawl_core/client/mongo_client.py
zcbot_crawl_core/client/portainer_client.py
zcbot_crawl_core/client/redis_client.py
zcbot_crawl_core/dao/__init__.py
zcbot_crawl_core/dao/auth_user_spider_group.py
zcbot_crawl_core/dao/batch_spider.py
zcbot_crawl_core/dao/batch_spider_group.py
zcbot_crawl_core/dao/meta.py
zcbot_crawl_core/dao/node.py
zcbot_crawl_core/dao/spider.py
zcbot_crawl_core/dao/spider_group.py
zcbot_crawl_core/dao/stream_spider.py
zcbot_crawl_core/dao/stream_spider_group.py
zcbot_crawl_core/model/__init__.py
zcbot_crawl_core/model/base.py
zcbot_crawl_core/model/batch.py
zcbot_crawl_core/model/entity.py
zcbot_crawl_core/model/enums.py
zcbot_crawl_core/model/rabbit.py
zcbot_crawl_core/model/stream.py
zcbot_crawl_core/publish/__init__.py
zcbot_crawl_core/publish/batch.py
zcbot_crawl_core/publish/stream.py
zcbot_crawl_core/receive/__init__.py
zcbot_crawl_core/receive/async_receuver.py
zcbot_crawl_core/receive/exceptions.py
zcbot_crawl_core/receive/key_builder.py
zcbot_crawl_core/receive/model.py
zcbot_crawl_core/receive/processor.py
zcbot_crawl_core/receive/receiver.py
zcbot_crawl_core/service/__init__.py
zcbot_crawl_core/service/base.py
zcbot_crawl_core/service/batch_spider.py
zcbot_crawl_core/service/batch_spider_group.py
zcbot_crawl_core/service/spider.py
zcbot_crawl_core/service/spider_group.py
zcbot_crawl_core/service/stream_spider.py
zcbot_crawl_core/service/stream_spider_group.py
zcbot_crawl_core/util/__init__.py
zcbot_crawl_core/util/cfg.py
zcbot_crawl_core/util/decator.py
zcbot_crawl_core/util/exceptions.py
zcbot_crawl_core/util/logger.py
zcbot_crawl_core/util/rabbit_key.py
zcbot_crawl_core/util/redis_key.py
zcbot_crawl_core/util/sequence.py
zcbot_crawl_core/util/time.py