Metadata-Version: 2.1
Name: zcbot-crawl-core
Version: 2.0.42
Summary: zcbot crawl core for zsodata
Home-page: http://www.zsodata.com
Author: zsodata
Author-email: team@zso.io
License: BSD License
Platform: all
Requires-Python: >=3.7
Requires-Dist: zcbot-url-parser
